cli/__init__.py
cli/main.py
topolograph/__init__.py
topolograph/client.py
topolograph/exceptions.py
topolograph_sdk-0.1.3.dist-info/licenses/LICENSE
topolograph_sdk-0.1.3.dist-info/METADATA
topolograph_sdk-0.1.3.dist-info/WHEEL
topolograph_sdk-0.1.3.dist-info/entry_points.txt
topolograph_sdk-0.1.3.dist-info/top_level.txt
topolograph_sdk-0.1.3.dist-info/RECORD
