Metadata-Version: 2.4
Name: topolograph-sdk
Version: 0.1.3
Summary: Python SDK for Topolograph - A Pythonic client for the Topolograph REST API with SSH-based topology ingestion
Author-email: Topolograph <info@topolograph.com>
License: Apache-2.0
Project-URL: Homepage, https://github.com/Vadims06/topolograph-sdk
Project-URL: Documentation, https://github.com/Vadims06/topolograph-sdk
Project-URL: Repository, https://github.com/Vadims06/topolograph-sdk
Project-URL: Issues, https://github.com/Vadims06/topolograph-sdk/issues
Keywords: topolograph,network,topology,ospf,isis,lsdb
Classifier: Development Status :: 3 - Alpha
Classifier: Intended Audience :: Developers
Classifier: Intended Audience :: System Administrators
Classifier: License :: OSI Approved :: Apache Software License
Classifier: Programming Language :: Python :: 3
Classifier: Programming Language :: Python :: 3.8
Classifier: Programming Language :: Python :: 3.9
Classifier: Programming Language :: Python :: 3.10
Classifier: Programming Language :: Python :: 3.11
Classifier: Topic :: System :: Networking
Classifier: Topic :: Software Development :: Libraries :: Python Modules
Requires-Python: >=3.8
License-File: LICENSE
Requires-Dist: requests>=2.28.0
Requires-Dist: nornir>=3.0.0
Requires-Dist: nornir-scrapli>=2022.1.0
Requires-Dist: typer>=0.9.0
Requires-Dist: pyyaml>=6.0
Requires-Dist: rich>=13.0.0
Provides-Extra: dev
Requires-Dist: pytest>=7.0.0; extra == "dev"
Requires-Dist: pytest-cov>=4.0.0; extra == "dev"
Requires-Dist: black>=23.0.0; extra == "dev"
Requires-Dist: ruff>=0.1.0; extra == "dev"
Dynamic: license-file
